onepower/__init__.py
onepower/add.py
onepower/bnl.py
onepower/hmi.py
onepower/hod.py
onepower/ia.py
onepower/pk.py
onepower/utils/poisson.py
onepower-0.7.0.dist-info/licenses/LICENSE.rst
onepower-0.7.0.dist-info/METADATA
onepower-0.7.0.dist-info/WHEEL
onepower-0.7.0.dist-info/top_level.txt
onepower-0.7.0.dist-info/RECORD
