Metadata-Version: 2.4
Name: onepower
Version: 0.7.0
Summary: Python package for computing power spectra and one-point statistics using the halo model framework.
Author-email: Andrej Dvornik <andrej.dvornik@me.com>, Maria Cristina Fortuna <maricri.fortuna@gmail.com>, Marika Asgari <marika.asgari@newcastle.ac.uk>
License-Expression: MIT
Project-URL: Homepage, https://github.com/KiDS-WL/onepower
Project-URL: Repository, https://github.com/KiDS-WL/onepower.git
Project-URL: Documentation, https://kids-wl.github.io/onepower/
Project-URL: Issues, https://github.com/KiDS-WL/onepower/issues
Project-URL: Changelog, https://github.com/KiDS-WL/onepower/blob/main/CHANGELOG.rst
Classifier: Development Status :: 5 - Production/Stable
Classifier: Intended Audience :: Science/Research
Classifier: Operating System :: POSIX
Classifier: Operating System :: Unix
Classifier: Programming Language :: Python
Classifier: Programming Language :: Python :: 3 :: Only
Classifier: Programming Language :: Python :: 3.10
Classifier: Programming Language :: Python :: 3.11
Classifier: Programming Language :: Python :: 3.12
Classifier: Programming Language :: Python :: Implementation :: CPython
Classifier: Natural Language :: English
Classifier: Topic :: Scientific/Engineering :: Physics
Classifier: Topic :: Scientific/Engineering :: Astronomy
Requires-Python: <3.13,>=3.10
License-File: LICENSE.rst
Requires-Dist: hmf>=3.5.2
Requires-Dist: numpy>=2.0
Requires-Dist: astropy>=6.0.0
Requires-Dist: dark_emulator==1.1.2
Requires-Dist: scipy<1.14.0
Requires-Dist: camb>=1.4.0
Requires-Dist: numexpr>=2.8.7
Requires-Dist: colossus>=1.3.5
Requires-Dist: hankel>=1.2.2
Requires-Dist: click
Requires-Dist: toml>=0.10.1
Requires-Dist: rich
Requires-Dist: pre-commit
Provides-Extra: docs
Requires-Dist: sphinx>=6.1.3; extra == "docs"
Requires-Dist: numpydoc>=0.8.0; extra == "docs"
Requires-Dist: nbsphinx; extra == "docs"
Requires-Dist: ipython; extra == "docs"
Requires-Dist: pandoc; extra == "docs"
Requires-Dist: sphinx_rtd_theme; extra == "docs"
Requires-Dist: pydata-sphinx-theme; extra == "docs"
Requires-Dist: importlib_metadata; extra == "docs"
Requires-Dist: ipykernel; extra == "docs"
Requires-Dist: docutils>=0.19; extra == "docs"
Provides-Extra: tests
Requires-Dist: coverage>=4.5.1; extra == "tests"
Requires-Dist: pytest>=3.5.1; extra == "tests"
Requires-Dist: pytest-cov>=2.5.1; extra == "tests"
Requires-Dist: pytest-plt; extra == "tests"
Requires-Dist: pytest-runner; extra == "tests"
Requires-Dist: PyYAML; extra == "tests"
Requires-Dist: mpmath>=1.0.0; extra == "tests"
Requires-Dist: numba; extra == "tests"
Provides-Extra: dev
Requires-Dist: onepower[docs,tests]; extra == "dev"
Provides-Extra: all
Requires-Dist: onepower[dev]; extra == "all"
Dynamic: license-file
